[
  {
    "name": "company-about",
    "path": "/company/about",
    "component": "/Users/majeongheum/virnect/pages/company/about.vue",
    "chunkName": "pages/company/about"
  },
  {
    "name": "company-aboutSub",
    "path": "/company/aboutSub",
    "component": "/Users/majeongheum/virnect/pages/company/aboutSub.vue",
    "chunkName": "pages/company/aboutSub"
  },
  {
    "name": "company-ir",
    "path": "/company/ir",
    "component": "/Users/majeongheum/virnect/pages/company/ir.vue",
    "chunkName": "pages/company/ir"
  },
  {
    "name": "company-ir-detail",
    "path": "/company/ir-detail",
    "component": "/Users/majeongheum/virnect/pages/company/ir-detail.vue",
    "chunkName": "pages/company/ir-detail"
  },
  {
    "name": "company-talent",
    "path": "/company/talent",
    "component": "/Users/majeongheum/virnect/pages/company/talent.vue",
    "chunkName": "pages/company/talent"
  },
  {
    "name": "news-detail",
    "path": "/news/detail",
    "component": "/Users/majeongheum/virnect/pages/news/detail.vue",
    "chunkName": "pages/news/detail"
  },
  {
    "name": "news-main",
    "path": "/news/main",
    "component": "/Users/majeongheum/virnect/pages/news/main.vue",
    "chunkName": "pages/news/main"
  },
  {
    "name": "policy-Payment",
    "path": "/policy/Payment",
    "component": "/Users/majeongheum/virnect/pages/policy/Payment.vue",
    "chunkName": "pages/policy/Payment"
  },
  {
    "name": "policy-Policy",
    "path": "/policy/Policy",
    "component": "/Users/majeongheum/virnect/pages/policy/Policy.vue",
    "chunkName": "pages/policy/Policy"
  },
  {
    "name": "policy-Terms",
    "path": "/policy/Terms",
    "component": "/Users/majeongheum/virnect/pages/policy/Terms.vue",
    "chunkName": "pages/policy/Terms"
  },
  {
    "name": "products-make",
    "path": "/products/make",
    "component": "/Users/majeongheum/virnect/pages/products/make.vue",
    "chunkName": "pages/products/make"
  },
  {
    "name": "products-ms",
    "path": "/products/ms",
    "component": "/Users/majeongheum/virnect/pages/products/ms.vue",
    "chunkName": "pages/products/ms"
  },
  {
    "name": "products-productsMain",
    "path": "/products/productsMain",
    "component": "/Users/majeongheum/virnect/pages/products/productsMain.vue",
    "chunkName": "pages/products/productsMain"
  },
  {
    "name": "products-remote",
    "path": "/products/remote",
    "component": "/Users/majeongheum/virnect/pages/products/remote.vue",
    "chunkName": "pages/products/remote"
  },
  {
    "name": "products-track",
    "path": "/products/track",
    "component": "/Users/majeongheum/virnect/pages/products/track.vue",
    "chunkName": "pages/products/track"
  },
  {
    "name": "products-twin",
    "path": "/products/twin",
    "component": "/Users/majeongheum/virnect/pages/products/twin.vue",
    "chunkName": "pages/products/twin"
  },
  {
    "name": "products-view",
    "path": "/products/view",
    "component": "/Users/majeongheum/virnect/pages/products/view.vue",
    "chunkName": "pages/products/view"
  },
  {
    "name": "solutions-airline_railroad",
    "path": "/solutions/airline_railroad",
    "component": "/Users/majeongheum/virnect/pages/solutions/airline_railroad.vue",
    "chunkName": "pages/solutions/airline_railroad"
  },
  {
    "name": "solutions-energy_resource",
    "path": "/solutions/energy_resource",
    "component": "/Users/majeongheum/virnect/pages/solutions/energy_resource.vue",
    "chunkName": "pages/solutions/energy_resource"
  },
  {
    "name": "solutions-epc",
    "path": "/solutions/epc",
    "component": "/Users/majeongheum/virnect/pages/solutions/epc.vue",
    "chunkName": "pages/solutions/epc"
  },
  {
    "name": "solutions-motor_parts",
    "path": "/solutions/motor_parts",
    "component": "/Users/majeongheum/virnect/pages/solutions/motor_parts.vue",
    "chunkName": "pages/solutions/motor_parts"
  },
  {
    "name": "solutions-oil_chemical_battery",
    "path": "/solutions/oil_chemical_battery",
    "component": "/Users/majeongheum/virnect/pages/solutions/oil_chemical_battery.vue",
    "chunkName": "pages/solutions/oil_chemical_battery"
  },
  {
    "name": "support-demo",
    "path": "/support/demo",
    "component": "/Users/majeongheum/virnect/pages/support/demo.vue",
    "chunkName": "pages/support/demo"
  },
  {
    "name": "support-faq",
    "path": "/support/faq",
    "component": "/Users/majeongheum/virnect/pages/support/faq.vue",
    "chunkName": "pages/support/faq"
  },
  {
    "name": "support-inquiry",
    "path": "/support/inquiry",
    "component": "/Users/majeongheum/virnect/pages/support/inquiry.vue",
    "chunkName": "pages/support/inquiry"
  },
  {
    "name": "support-learning-center",
    "path": "/support/learning-center",
    "component": "/Users/majeongheum/virnect/pages/support/learning-center.vue",
    "chunkName": "pages/support/learning-center"
  },
  {
    "name": "support-learning-manual-detail",
    "path": "/support/learning-manual-detail",
    "component": "/Users/majeongheum/virnect/pages/support/learning-manual-detail.vue",
    "chunkName": "pages/support/learning-manual-detail"
  },
  {
    "name": "support-learning-video-detail",
    "path": "/support/learning-video-detail",
    "component": "/Users/majeongheum/virnect/pages/support/learning-video-detail.vue",
    "chunkName": "pages/support/learning-video-detail"
  },
  {
    "name": "support-notice",
    "path": "/support/notice",
    "component": "/Users/majeongheum/virnect/pages/support/notice.vue",
    "chunkName": "pages/support/notice"
  },
  {
    "name": "support-notice-detail",
    "path": "/support/notice-detail",
    "component": "/Users/majeongheum/virnect/pages/support/notice-detail.vue",
    "chunkName": "pages/support/notice-detail"
  },
  {
    "name": "support-supportSubMain",
    "path": "/support/supportSubMain",
    "component": "/Users/majeongheum/virnect/pages/support/supportSubMain.vue",
    "chunkName": "pages/support/supportSubMain"
  },
  {
    "name": "company-subCompany-Brand",
    "path": "/company/subCompany/Brand",
    "component": "/Users/majeongheum/virnect/pages/company/subCompany/Brand.vue",
    "chunkName": "pages/company/subCompany/Brand"
  },
  {
    "name": "index",
    "path": "/",
    "component": "/Users/majeongheum/virnect/pages/index.vue",
    "chunkName": "pages/index"
  }
]
